flip_qwen_backend/__init__.py
flip_qwen_backend/client.py
flip_qwen_backend-0.1.0.dist-info/METADATA
flip_qwen_backend-0.1.0.dist-info/WHEEL
flip_qwen_backend-0.1.0.dist-info/top_level.txt
flip_qwen_backend-0.1.0.dist-info/RECORD
