Metadata-Version: 2.1
Name: flip_qwen_backend
Version: 0.1.0
Summary: A lightweight SDK for accessing backend server pools
Author: Hongwei Zhang
Author-email: hongwei.zhang@flip.shop
Requires-Python: >=3.6
Requires-Dist: requests
